gsheetlog.py
gsheetlog-0.4.0.dist-info/DESCRIPTION.rst
gsheetlog-0.4.0.dist-info/METADATA
gsheetlog-0.4.0.dist-info/RECORD
gsheetlog-0.4.0.dist-info/WHEEL
gsheetlog-0.4.0.dist-info/entry_points.txt
gsheetlog-0.4.0.dist-info/metadata.json
gsheetlog-0.4.0.dist-info/top_level.txt
