Metadata-Version: 2.0
Name: gsheetlog
Version: 0.4.0
Summary: Extract Google Sheet history
Home-page: UNKNOWN
Author: Sergey Salnikov
Author-email: serg@salnikov.ru
License: UNKNOWN
Platform: UNKNOWN
Classifier: Development Status :: 3 - Alpha
Classifier: License :: OSI Approved :: MIT License
Classifier: Programming Language :: Python :: 3
Classifier: Programming Language :: Python :: 3.6
Requires-Dist: click
Requires-Dist: google-api-python-client
Requires-Dist: ratelimit
